{"target": -2798.1388100000013, "params": {"spark.default.parallelism": 495.1632848270786, "spark.executor.cores": 2.9917134217176886, "spark.executor.instances": 5.877781520477846, "spark.executor.memory": 6.324589862773344, "spark.executor.memoryOverhead": 720.5851386778668, "spark.memory.fraction": 0.7705075340682019, "spark.memory.storageFraction": 0.6256444185392679, "spark.reducer.maxBlocksInFlightPerAddress": 1811203091.786459, "spark.reducer.maxSizeInFlight": 58.32570239875492, "spark.shuffle.file.buffer": 40.850637282602406}, "datetime": {"datetime": "2022-01-06 15:21:02", "elapsed": 0.0, "delta": 0.0}}
{"target": -2794.071830000001, "params": {"spark.default.parallelism": 393.62480077394855, "spark.executor.cores": 1.3112264953442037, "spark.executor.instances": 5.347899515121364, "spark.executor.memory": 6.807882896124381, "spark.executor.memoryOverhead": 768.1233990702774, "spark.memory.fraction": 0.6768075549543228, "spark.memory.storageFraction": 0.5328248294565063, "spark.reducer.maxBlocksInFlightPerAddress": 1863399382.042508, "spark.reducer.maxSizeInFlight": 46.55961855607636, "spark.shuffle.file.buffer": 41.891550148439485}, "datetime": {"datetime": "2022-01-06 15:21:02", "elapsed": 0.027986, "delta": 0.027986}}
{"target": -2799.314560000001, "params": {"spark.default.parallelism": 439.49353562576493, "spark.executor.cores": 2.780441026464336, "spark.executor.instances": 5.5353812096438535, "spark.executor.memory": 3.2128167808515924, "spark.executor.memoryOverhead": 614.5526348519685, "spark.memory.fraction": 0.6475163363862105, "spark.memory.storageFraction": 0.8726400187065675, "spark.reducer.maxBlocksInFlightPerAddress": 1241493984.582063, "spark.reducer.maxSizeInFlight": 65.19086666757045, "spark.shuffle.file.buffer": 26.15153857257648}, "datetime": {"datetime": "2022-01-06 15:21:02", "elapsed": 0.052892, "delta": 0.024906}}
{"target": -2811.257570000001, "params": {"spark.default.parallelism": 397.9590439470519, "spark.executor.cores": 1.9865603944175345, "spark.executor.instances": 5.02359063524803, "spark.executor.memory": 4.630629206250212, "spark.executor.memoryOverhead": 854.7400138249202, "spark.memory.fraction": 0.8360749247140028, "spark.memory.storageFraction": 0.7845439320357916, "spark.reducer.maxBlocksInFlightPerAddress": 2119886112.489381, "spark.reducer.maxSizeInFlight": 63.38236211770591, "spark.shuffle.file.buffer": 36.43759103481051}, "datetime": {"datetime": "2022-01-06 15:21:02", "elapsed": 0.078822, "delta": 0.02593}}
{"target": -2801.0149700000015, "params": {"spark.default.parallelism": 446.6940830659821, "spark.executor.cores": 1.4700672950258542, "spark.executor.instances": 6.754848540800028, "spark.executor.memory": 4.233906843515191, "spark.executor.memoryOverhead": 418.03626659759897, "spark.memory.fraction": 0.6890585730401584, "spark.memory.storageFraction": 0.8343883231322995, "spark.reducer.maxBlocksInFlightPerAddress": 1590130638.8638844, "spark.reducer.maxSizeInFlight": 32.6629048376293, "spark.shuffle.file.buffer": 33.44658880337438}, "datetime": {"datetime": "2022-01-06 15:21:02", "elapsed": 0.104757, "delta": 0.025935}}
{"target": -2809.695000000001, "params": {"spark.default.parallelism": 366.39012506403026, "spark.executor.cores": 2.2686313562994123, "spark.executor.instances": 4.101993519814173, "spark.executor.memory": 5.546495831319989, "spark.executor.memoryOverhead": 459.2669215266555, "spark.memory.fraction": 0.5474653582539081, "spark.memory.storageFraction": 0.8486313317836538, "spark.reducer.maxBlocksInFlightPerAddress": 1944685550.5839171, "spark.reducer.maxSizeInFlight": 71.54071433034437, "spark.shuffle.file.buffer": 23.733360679130193}, "datetime": {"datetime": "2022-01-06 15:21:02", "elapsed": 0.131713, "delta": 0.026956}}
{"target": -2800.052250000002, "params": {"spark.default.parallelism": 305.9324631709123, "spark.executor.cores": 2.650816904150373, "spark.executor.instances": 6.852092336906095, "spark.executor.memory": 6.535151721580945, "spark.executor.memoryOverhead": 676.8677318669497, "spark.memory.fraction": 0.6310821891582388, "spark.memory.storageFraction": 0.712950155269225, "spark.reducer.maxBlocksInFlightPerAddress": 1657683639.7768703, "spark.reducer.maxSizeInFlight": 36.146414146840584, "spark.shuffle.file.buffer": 18.076614175068553}, "datetime": {"datetime": "2022-01-06 15:21:02", "elapsed": 0.156619, "delta": 0.024906}}
{"target": -2797.1336800000013, "params": {"spark.default.parallelism": 237.96555665017303, "spark.executor.cores": 1.5027982666154678, "spark.executor.instances": 7.672248488272775, "spark.executor.memory": 3.757943773862005, "spark.executor.memoryOverhead": 691.3595542211316, "spark.memory.fraction": 0.800732362105167, "spark.memory.storageFraction": 0.5761820184487463, "spark.reducer.maxBlocksInFlightPerAddress": 1398366939.6778803, "spark.reducer.maxSizeInFlight": 41.728926240224226, "spark.shuffle.file.buffer": 45.5441992580288}, "datetime": {"datetime": "2022-01-06 15:21:02", "elapsed": 0.181554, "delta": 0.024935}}
{"target": -2797.8836300000007, "params": {"spark.default.parallelism": 274.6522900893701, "spark.executor.cores": 1.1608468751557577, "spark.executor.instances": 7.047410721429895, "spark.executor.memory": 5.136439598050264, "spark.executor.memoryOverhead": 642.0033601295324, "spark.memory.fraction": 0.7260094309338994, "spark.memory.storageFraction": 0.5483136927049775, "spark.reducer.maxBlocksInFlightPerAddress": 1174184085.656222, "spark.reducer.maxSizeInFlight": 26.703397541551244, "spark.shuffle.file.buffer": 30.671767587653463}, "datetime": {"datetime": "2022-01-06 15:21:02", "elapsed": 0.207515, "delta": 0.025961}}
{"target": -2810.5635500000003, "params": {"spark.default.parallelism": 415.0808436646232, "spark.executor.cores": 1.8005059527615885, "spark.executor.instances": 4.510023679118874, "spark.executor.memory": 5.221582558261428, "spark.executor.memoryOverhead": 732.8182358800623, "spark.memory.fraction": 0.7003606852639676, "spark.memory.storageFraction": 0.6908697151678961, "spark.reducer.maxBlocksInFlightPerAddress": 2043072976.974533, "spark.reducer.maxSizeInFlight": 38.823124557668486, "spark.shuffle.file.buffer": 21.118060435866596}, "datetime": {"datetime": "2022-01-06 15:21:02", "elapsed": 0.239399, "delta": 0.031884}}
{"target": -2800.504710000002, "params": {"spark.default.parallelism": 201.06029309667468, "spark.executor.cores": 2.351219455730579, "spark.executor.instances": 4.664736133872751, "spark.executor.memory": 4.141656786378945, "spark.executor.memoryOverhead": 802.3234751079096, "spark.memory.fraction": 0.7558386011323643, "spark.memory.storageFraction": 0.882949113281549, "spark.reducer.maxBlocksInFlightPerAddress": 1756299188.741991, "spark.reducer.maxSizeInFlight": 25.056145219136305, "spark.shuffle.file.buffer": 24.550071985504484}, "datetime": {"datetime": "2022-01-06 15:21:02", "elapsed": 0.264358, "delta": 0.024959}}
{"target": -2797.4055700000013, "params": {"spark.default.parallelism": 275.775501944214, "spark.executor.cores": 2.8895536467894516, "spark.executor.instances": 5.611210629654302, "spark.executor.memory": 3.1002352843533645, "spark.executor.memoryOverhead": 407.135130331645, "spark.memory.fraction": 0.8678362491252483, "spark.memory.storageFraction": 0.5195566484708998, "spark.reducer.maxBlocksInFlightPerAddress": 1547198011.3552408, "spark.reducer.maxSizeInFlight": 69.16145806255406, "spark.shuffle.file.buffer": 27.38334388569357}, "datetime": {"datetime": "2022-01-06 15:21:02", "elapsed": 0.289265, "delta": 0.024907}}
{"target": -2813.5556300000007, "params": {"spark.default.parallelism": 227.09624428431442, "spark.executor.cores": 1.2034891910464658, "spark.executor.instances": 4.389357359144775, "spark.executor.memory": 5.695248242094142, "spark.executor.memoryOverhead": 838.4854285779378, "spark.memory.fraction": 0.618448303913583, "spark.memory.storageFraction": 0.7519262335762329, "spark.reducer.maxBlocksInFlightPerAddress": 2023593172.214561, "spark.reducer.maxSizeInFlight": 29.144783930516247, "spark.shuffle.file.buffer": 20.45480480386293}, "datetime": {"datetime": "2022-01-06 15:21:02", "elapsed": 0.314198, "delta": 0.024933}}
{"target": -2853.710520000001, "params": {"spark.default.parallelism": 245.83225243808755, "spark.executor.cores": 2.16222119887363, "spark.executor.instances": 7.25770520057393, "spark.executor.memory": 4.460659129513717, "spark.executor.memoryOverhead": 603.0672533953237, "spark.memory.fraction": 0.5102555711700746, "spark.memory.storageFraction": 0.6521658278047712, "spark.reducer.maxBlocksInFlightPerAddress": 1104538378.9071696, "spark.reducer.maxSizeInFlight": 54.1361279525293, "spark.shuffle.file.buffer": 16.137634321830912}, "datetime": {"datetime": "2022-01-06 15:21:02", "elapsed": 0.347109, "delta": 0.032911}}
{"target": -2799.7993900000015, "params": {"spark.default.parallelism": 327.9588311236196, "spark.executor.cores": 1.721785646022655, "spark.executor.instances": 7.522484778415523, "spark.executor.memory": 6.079140214322418, "spark.executor.memoryOverhead": 817.319354487503, "spark.memory.fraction": 0.5999875744755316, "spark.memory.storageFraction": 0.7745140547856757, "spark.reducer.maxBlocksInFlightPerAddress": 1702140047.7963746, "spark.reducer.maxSizeInFlight": 43.352019317403105, "spark.shuffle.file.buffer": 34.47804127512025}, "datetime": {"datetime": "2022-01-06 15:21:02", "elapsed": 0.381018, "delta": 0.033909}}
{"target": -2797.3622200000013, "params": {"spark.default.parallelism": 474.5863231102833, "spark.executor.cores": 2.52882862570055, "spark.executor.instances": 7.929592058583, "spark.executor.memory": 3.5064029138276904, "spark.executor.memoryOverhead": 560.5415626781255, "spark.memory.fraction": 0.8836633208059166, "spark.memory.storageFraction": 0.8050001194718515, "spark.reducer.maxBlocksInFlightPerAddress": 1322988689.7237675, "spark.reducer.maxSizeInFlight": 55.26191643702213, "spark.shuffle.file.buffer": 29.119349637570938}, "datetime": {"datetime": "2022-01-06 15:21:02", "elapsed": 0.423931, "delta": 0.042913}}
{"target": -2797.479190000001, "params": {"spark.default.parallelism": 294.5188768723892, "spark.executor.cores": 1.004867312610455, "spark.executor.instances": 6.5169394455484735, "spark.executor.memory": 5.976290055527343, "spark.executor.memoryOverhead": 519.1684646773449, "spark.memory.fraction": 0.5264688121577135, "spark.memory.storageFraction": 0.5866962103611325, "spark.reducer.maxBlocksInFlightPerAddress": 1484650208.9990764, "spark.reducer.maxSizeInFlight": 48.05678093992752, "spark.shuffle.file.buffer": 47.392965848645076}, "datetime": {"datetime": "2022-01-06 15:21:02", "elapsed": 0.452826, "delta": 0.028895}}
{"target": -2797.3600100000012, "params": {"spark.default.parallelism": 360.57487121315467, "spark.executor.cores": 1.6654215122908917, "spark.executor.instances": 6.005657114970223, "spark.executor.memory": 3.8558636914695006, "spark.executor.memoryOverhead": 533.3799144745296, "spark.memory.fraction": 0.5788450751059929, "spark.memory.storageFraction": 0.6009669346010591, "spark.reducer.maxBlocksInFlightPerAddress": 1383573883.9214416, "spark.reducer.maxSizeInFlight": 52.72873311468025, "spark.shuffle.file.buffer": 44.67289677586725}, "datetime": {"datetime": "2022-01-06 15:21:02", "elapsed": 0.483767, "delta": 0.030941}}
{"target": -2800.3464300000005, "params": {"spark.default.parallelism": 339.64210084679644, "spark.executor.cores": 2.0817063033937515, "spark.executor.instances": 6.212716639516319, "spark.executor.memory": 4.819241632418509, "spark.executor.memoryOverhead": 456.582938481311, "spark.memory.fraction": 0.7915990378169871, "spark.memory.storageFraction": 0.6647341783230643, "spark.reducer.maxBlocksInFlightPerAddress": 1232267600.8072777, "spark.reducer.maxSizeInFlight": 61.21986833953144, "spark.shuffle.file.buffer": 37.95609821504781}, "datetime": {"datetime": "2022-01-06 15:21:03", "elapsed": 0.508593, "delta": 0.024826}}
{"target": -2796.736680000002, "params": {"spark.default.parallelism": 455.6230461291243, "spark.executor.cores": 2.4026633249462863, "spark.executor.instances": 4.921720932770886, "spark.executor.memory": 6.603709826267096, "spark.executor.memoryOverhead": 490.3897768591645, "spark.memory.fraction": 0.8594022150537025, "spark.memory.storageFraction": 0.723091393756967, "spark.reducer.maxBlocksInFlightPerAddress": 1895230982.4996514, "spark.reducer.maxSizeInFlight": 34.404260122909754, "spark.shuffle.file.buffer": 39.315547469058814}, "datetime": {"datetime": "2022-01-06 15:21:03", "elapsed": 0.533574, "delta": 0.024981}}
{"target": -2807.7430000000018, "params": {"spark.default.parallelism": 271.10809407290833, "spark.executor.cores": 2.806759041124508, "spark.executor.instances": 6.294717946689143, "spark.executor.memory": 3.011481308124636, "spark.executor.memoryOverhead": 688.2524424150168, "spark.memory.fraction": 0.6306579607088385, "spark.memory.storageFraction": 0.7108232409030437, "spark.reducer.maxBlocksInFlightPerAddress": 2025014908.6723402, "spark.reducer.maxSizeInFlight": 41.14894848011999, "spark.shuffle.file.buffer": 45.073124829433574}, "datetime": {"datetime": "2022-01-06 15:21:03", "elapsed": 1.036275, "delta": 0.502701}}
{"target": -2799.283210000001, "params": {"spark.default.parallelism": 208.6782914450098, "spark.executor.cores": 2.8715228789085936, "spark.executor.instances": 4.172397754905537, "spark.executor.memory": 5.332302066416251, "spark.executor.memoryOverhead": 506.328193524531, "spark.memory.fraction": 0.7776942044115536, "spark.memory.storageFraction": 0.6789340623474521, "spark.reducer.maxBlocksInFlightPerAddress": 1863250243.6977942, "spark.reducer.maxSizeInFlight": 59.51821597556469, "spark.shuffle.file.buffer": 22.367162975703053}, "datetime": {"datetime": "2022-01-06 15:21:03", "elapsed": 1.470091, "delta": 0.433816}}
{"target": -2797.6639300000015, "params": {"spark.default.parallelism": 253.7053463064529, "spark.executor.cores": 2.023141842675955, "spark.executor.instances": 4.844227446733344, "spark.executor.memory": 5.0194466650139775, "spark.executor.memoryOverhead": 513.5744052608084, "spark.memory.fraction": 0.8986607823810616, "spark.memory.storageFraction": 0.7336572422810366, "spark.reducer.maxBlocksInFlightPerAddress": 1895422059.0286393, "spark.reducer.maxSizeInFlight": 51.72672195271362, "spark.shuffle.file.buffer": 37.23331125902117}, "datetime": {"datetime": "2022-01-06 15:21:04", "elapsed": 1.936117, "delta": 0.466026}}
{"target": -2797.8902700000017, "params": {"spark.default.parallelism": 232.70562920572047, "spark.executor.cores": 2.2675735212238357, "spark.executor.instances": 7.2118529494949515, "spark.executor.memory": 5.787201984480713, "spark.executor.memoryOverhead": 761.7422108703548, "spark.memory.fraction": 0.636981647937408, "spark.memory.storageFraction": 0.838340593211071, "spark.reducer.maxBlocksInFlightPerAddress": 1534128789.5421472, "spark.reducer.maxSizeInFlight": 63.5524737797913, "spark.shuffle.file.buffer": 36.0478770759774}, "datetime": {"datetime": "2022-01-06 15:21:04", "elapsed": 2.374361, "delta": 0.438244}}
{"target": -2810.852080000001, "params": {"spark.default.parallelism": 349.1750280081594, "spark.executor.cores": 2.0380319681473575, "spark.executor.instances": 4.69888060043569, "spark.executor.memory": 5.282863406185026, "spark.executor.memoryOverhead": 875.3994386276474, "spark.memory.fraction": 0.8267340435166488, "spark.memory.storageFraction": 0.7377490495323911, "spark.reducer.maxBlocksInFlightPerAddress": 2121702105.4336865, "spark.reducer.maxSizeInFlight": 67.27500406412742, "spark.shuffle.file.buffer": 35.05945387528466}, "datetime": {"datetime": "2022-01-06 15:21:05", "elapsed": 2.819677, "delta": 0.445316}}
{"target": -2799.4428500000013, "params": {"spark.default.parallelism": 244.02544422928824, "spark.executor.cores": 2.4586378387222467, "spark.executor.instances": 4.754980267508744, "spark.executor.memory": 5.575582577246651, "spark.executor.memoryOverhead": 755.8728336341153, "spark.memory.fraction": 0.5842929568333283, "spark.memory.storageFraction": 0.740381699243056, "spark.reducer.maxBlocksInFlightPerAddress": 1877897542.6818209, "spark.reducer.maxSizeInFlight": 54.634498109776004, "spark.shuffle.file.buffer": 35.10807369429277}, "datetime": {"datetime": "2022-01-06 15:21:05", "elapsed": 3.259219, "delta": 0.439542}}
{"target": -2800.6123900000016, "params": {"spark.default.parallelism": 455.35555822703645, "spark.executor.cores": 1.0595659608538661, "spark.executor.instances": 7.385839558292474, "spark.executor.memory": 4.798075442935514, "spark.executor.memoryOverhead": 654.5387395539915, "spark.memory.fraction": 0.7650726001722787, "spark.memory.storageFraction": 0.7514844609932246, "spark.reducer.maxBlocksInFlightPerAddress": 1863533729.0028958, "spark.reducer.maxSizeInFlight": 57.70600827386979, "spark.shuffle.file.buffer": 29.388092269543616}, "datetime": {"datetime": "2022-01-06 15:21:06", "elapsed": 3.711406, "delta": 0.452187}}
{"target": -2797.0438800000015, "params": {"spark.default.parallelism": 362.632271694691, "spark.executor.cores": 1.2728029635944753, "spark.executor.instances": 6.88821093390113, "spark.executor.memory": 4.180747465852329, "spark.executor.memoryOverhead": 777.2915459267549, "spark.memory.fraction": 0.7965422516045646, "spark.memory.storageFraction": 0.6038469428435012, "spark.reducer.maxBlocksInFlightPerAddress": 1398541631.4759393, "spark.reducer.maxSizeInFlight": 50.79642172039525, "spark.shuffle.file.buffer": 42.5164129398474}, "datetime": {"datetime": "2022-01-06 15:21:06", "elapsed": 4.188167, "delta": 0.476761}}
{"target": -2795.2315000000012, "params": {"spark.default.parallelism": 489.77991950591667, "spark.executor.cores": 1.2187658283871692, "spark.executor.instances": 6.692164216866487, "spark.executor.memory": 4.9997294843968, "spark.executor.memoryOverhead": 767.1094270329611, "spark.memory.fraction": 0.5574427991496838, "spark.memory.storageFraction": 0.5332810545743503, "spark.reducer.maxBlocksInFlightPerAddress": 1502399536.48588, "spark.reducer.maxSizeInFlight": 62.254188095035204, "spark.shuffle.file.buffer": 22.133623645116483}, "datetime": {"datetime": "2022-01-06 15:21:07", "elapsed": 4.647956, "delta": 0.459789}}
{"target": -2798.7965400000016, "params": {"spark.default.parallelism": 212.98728145584758, "spark.executor.cores": 1.9728814863407895, "spark.executor.instances": 4.957644176551024, "spark.executor.memory": 6.809895126773037, "spark.executor.memoryOverhead": 849.3390654974114, "spark.memory.fraction": 0.7455736009538804, "spark.memory.storageFraction": 0.8893949589300785, "spark.reducer.maxBlocksInFlightPerAddress": 1444033871.2289782, "spark.reducer.maxSizeInFlight": 67.09683444804872, "spark.shuffle.file.buffer": 29.907039149072304}, "datetime": {"datetime": "2022-01-06 15:21:07", "elapsed": 5.147976, "delta": 0.50002}}
{"target": -2801.355440000001, "params": {"spark.default.parallelism": 481.6966416734874, "spark.executor.cores": 2.0302306210880916, "spark.executor.instances": 6.2807869442258895, "spark.executor.memory": 6.948657588083437, "spark.executor.memoryOverhead": 812.2517562493692, "spark.memory.fraction": 0.7872020636822256, "spark.memory.storageFraction": 0.7881553639756516, "spark.reducer.maxBlocksInFlightPerAddress": 1502229293.7019947, "spark.reducer.maxSizeInFlight": 45.87633776127565, "spark.shuffle.file.buffer": 19.17615421308396}, "datetime": {"datetime": "2022-01-06 15:21:08", "elapsed": 5.595947, "delta": 0.447971}}
{"target": -2798.096950000001, "params": {"spark.default.parallelism": 282.6809308282576, "spark.executor.cores": 2.8494816270767434, "spark.executor.instances": 5.547956937025169, "spark.executor.memory": 4.971523493725281, "spark.executor.memoryOverhead": 509.4379844410101, "spark.memory.fraction": 0.8539866075352254, "spark.memory.storageFraction": 0.6533053827221147, "spark.reducer.maxBlocksInFlightPerAddress": 1393260240.5974011, "spark.reducer.maxSizeInFlight": 58.444558185348214, "spark.shuffle.file.buffer": 22.107838181513838}, "datetime": {"datetime": "2022-01-06 15:21:08", "elapsed": 6.063835, "delta": 0.467888}}
{"target": -2799.51489, "params": {"spark.default.parallelism": 360.44966975594343, "spark.executor.cores": 2.535925756562623, "spark.executor.instances": 4.2123703818101, "spark.executor.memory": 5.196213775402079, "spark.executor.memoryOverhead": 778.8903160085895, "spark.memory.fraction": 0.7598332219513916, "spark.memory.storageFraction": 0.8725788059971643, "spark.reducer.maxBlocksInFlightPerAddress": 1153984101.0803053, "spark.reducer.maxSizeInFlight": 37.286710204828154, "spark.shuffle.file.buffer": 45.41560013619752}, "datetime": {"datetime": "2022-01-06 15:21:09", "elapsed": 6.494011, "delta": 0.430176}}
{"target": -2798.1814900000013, "params": {"spark.default.parallelism": 427.3210770047533, "spark.executor.cores": 2.3134441286346004, "spark.executor.instances": 6.336050125317557, "spark.executor.memory": 5.800770023533673, "spark.executor.memoryOverhead": 689.3833859882748, "spark.memory.fraction": 0.5999773222642624, "spark.memory.storageFraction": 0.5740621819881756, "spark.reducer.maxBlocksInFlightPerAddress": 1502530605.5939198, "spark.reducer.maxSizeInFlight": 29.16869684649144, "spark.shuffle.file.buffer": 26.944676910529594}, "datetime": {"datetime": "2022-01-06 15:21:09", "elapsed": 7.008477, "delta": 0.514466}}
{"target": -2796.3445000000006, "params": {"spark.default.parallelism": 253.54844989324647, "spark.executor.cores": 2.939741140689428, "spark.executor.instances": 6.967758101824307, "spark.executor.memory": 4.039166773217659, "spark.executor.memoryOverhead": 670.5490237495476, "spark.memory.fraction": 0.8821049014152748, "spark.memory.storageFraction": 0.5323015631248316, "spark.reducer.maxBlocksInFlightPerAddress": 1163435994.8568676, "spark.reducer.maxSizeInFlight": 53.71847190815555, "spark.shuffle.file.buffer": 23.183791322750647}, "datetime": {"datetime": "2022-01-06 15:21:09", "elapsed": 7.464469, "delta": 0.455992}}
{"target": -2798.572950000001, "params": {"spark.default.parallelism": 263.5164004545459, "spark.executor.cores": 2.6603130523245984, "spark.executor.instances": 4.960380616644841, "spark.executor.memory": 5.52648298100064, "spark.executor.memoryOverhead": 734.394607960496, "spark.memory.fraction": 0.7969533718828408, "spark.memory.storageFraction": 0.6561058818398324, "spark.reducer.maxBlocksInFlightPerAddress": 1889598130.3914661, "spark.reducer.maxSizeInFlight": 67.34092330184208, "spark.shuffle.file.buffer": 34.79744061560246}, "datetime": {"datetime": "2022-01-06 15:21:10", "elapsed": 7.9304, "delta": 0.465931}}
{"target": -2797.082490000001, "params": {"spark.default.parallelism": 454.2880127718163, "spark.executor.cores": 2.3180713193317666, "spark.executor.instances": 5.515324674646927, "spark.executor.memory": 4.66626691605899, "spark.executor.memoryOverhead": 621.7018836236315, "spark.memory.fraction": 0.8741135080027203, "spark.memory.storageFraction": 0.845437181967241, "spark.reducer.maxBlocksInFlightPerAddress": 1586908648.5908895, "spark.reducer.maxSizeInFlight": 50.61688791735202, "spark.shuffle.file.buffer": 44.01292359293829}, "datetime": {"datetime": "2022-01-06 15:21:10", "elapsed": 8.398957, "delta": 0.468557}}
{"target": -2798.7868500000013, "params": {"spark.default.parallelism": 452.62636499163295, "spark.executor.cores": 2.0660050966719945, "spark.executor.instances": 5.709941589971207, "spark.executor.memory": 3.9649633735922762, "spark.executor.memoryOverhead": 694.8163216742546, "spark.memory.fraction": 0.6654374067579883, "spark.memory.storageFraction": 0.5953435336342447, "spark.reducer.maxBlocksInFlightPerAddress": 1163636074.7589436, "spark.reducer.maxSizeInFlight": 51.051648817793705, "spark.shuffle.file.buffer": 24.297023076989504}, "datetime": {"datetime": "2022-01-06 15:21:11", "elapsed": 8.883902, "delta": 0.484945}}
{"target": -2803.3084400000016, "params": {"spark.default.parallelism": 229.9736412707366, "spark.executor.cores": 2.4354091812773886, "spark.executor.instances": 5.919121921468676, "spark.executor.memory": 5.3668197487308715, "spark.executor.memoryOverhead": 451.7883314259724, "spark.memory.fraction": 0.818516964162448, "spark.memory.storageFraction": 0.5795256894902618, "spark.reducer.maxBlocksInFlightPerAddress": 1895054268.0878913, "spark.reducer.maxSizeInFlight": 69.52696744767235, "spark.shuffle.file.buffer": 20.664685266452118}, "datetime": {"datetime": "2022-01-06 15:21:11", "elapsed": 9.337392, "delta": 0.45349}}
{"target": -2797.6824300000003, "params": {"spark.default.parallelism": 324.6217244638715, "spark.executor.cores": 1.5137172553472538, "spark.executor.instances": 7.536317576393012, "spark.executor.memory": 6.170934869473125, "spark.executor.memoryOverhead": 501.53861796555873, "spark.memory.fraction": 0.6706282558157216, "spark.memory.storageFraction": 0.6612156960531659, "spark.reducer.maxBlocksInFlightPerAddress": 1163256027.1021712, "spark.reducer.maxSizeInFlight": 35.75267168290952, "spark.shuffle.file.buffer": 45.58159911734015}, "datetime": {"datetime": "2022-01-06 15:21:12", "elapsed": 9.772055, "delta": 0.434663}}
"{'maxIndex': 2, 'target': -2794.071830000001, 'params': {'spark.default.parallelism': 393.62480077394855, 'spark.executor.cores': 1.3112264953442037, 'spark.executor.instances': 5.347899515121364, 'spark.executor.memory': 6.807882896124381, 'spark.executor.memoryOverhead': 768.1233990702774, 'spark.memory.fraction': 0.6768075549543228, 'spark.memory.storageFraction': 0.5328248294565063, 'spark.reducer.maxBlocksInFlightPerAddress': 1863399382.042508, 'spark.reducer.maxSizeInFlight': 46.55961855607636, 'spark.shuffle.file.buffer': 41.891550148439485}}"